git_mcp_server/__init__.py
git_mcp_server/server.py
git_mcp_server/tools/__init__.py
git_mcp_server/tools/branch.py
git_mcp_server/tools/commit.py
git_mcp_server/tools/remote.py
git_mcp_server/tools/status.py
git_mcp_server/tools/sync.py
git_mcp_server/utils/__init__.py
git_mcp_server/utils/errors.py
git_mcp_server/utils/git_client.py
rriesco_mcp_git-0.1.5.dist-info/licenses/LICENSE
rriesco_mcp_git-0.1.5.dist-info/METADATA
rriesco_mcp_git-0.1.5.dist-info/WHEEL
rriesco_mcp_git-0.1.5.dist-info/entry_points.txt
rriesco_mcp_git-0.1.5.dist-info/top_level.txt
rriesco_mcp_git-0.1.5.dist-info/RECORD
