Metadata-Version: 2.4
Name: rriesco-mcp-git
Version: 0.1.5
Summary: MCP server for local git operations - commit, branch, push, pull, sync
Author-email: Rafael Riesco <rriesco@users.noreply.github.com>
License: MIT
Project-URL: Homepage, https://github.com/rriesco/git-mcp-server
Project-URL: Repository, https://github.com/rriesco/git-mcp-server
Project-URL: Issues, https://github.com/rriesco/git-mcp-server/issues
Keywords: mcp,git,claude,anthropic,automation,version-control
Classifier: Development Status :: 4 - Beta
Classifier: Intended Audience :: Developers
Classifier: License :: OSI Approved :: MIT License
Classifier: Programming Language :: Python :: 3
Classifier: Programming Language :: Python :: 3.10
Classifier: Programming Language :: Python :: 3.11
Classifier: Programming Language :: Python :: 3.12
Classifier: Topic :: Software Development :: Version Control :: Git
Requires-Python: >=3.10
License-File: LICENSE
Requires-Dist: mcp>=1.1.0
Requires-Dist: gitpython>=3.1.0
Requires-Dist: pydantic>=2.0.0
Provides-Extra: dev
Requires-Dist: pytest>=8.0.0; extra == "dev"
Requires-Dist: pytest-cov>=4.1.0; extra == "dev"
Requires-Dist: mypy>=1.8.0; extra == "dev"
Requires-Dist: ruff>=0.1.0; extra == "dev"
Dynamic: license-file
